Workbook
Name mu_d: Inputs!$C$4
Name sigma_d: Inputs!$C$5
Name L_nom: Inputs!$C$6
Name L_excess: Inputs!$C$7
Name sigma_LT: Inputs!$C$8
Name unit_cost: Inputs!$C$9
Name unit_price: Inputs!$C$10
Name unit_margin: Inputs!$C$11
Name shelf_life: Inputs!$C$12
Name n_stores: Inputs!$C$13
Name n_skus: Inputs!$C$14
Name holding_rate: Inputs!$C$17
Name cycle_days: Inputs!$C$18
Name days_month: Inputs!$C$19
Name obs_units: Inputs!$C$22
Name seg_rev_loss: Inputs!$C$23
Name seg_mgn_loss: Inputs!$C$24
Name L_act: Inputs!$C$27
Name sigma_DL: Inputs!$C$28
Name order_qty: Inputs!$C$29
Name cycles_pm: Inputs!$C$30
Name rop_current: Inputs!$C$31
Name z_current: Inputs!$C$32
Name calib: Inputs!$C$33
Name hold_unit_cycle: Inputs!$C$34
Name crit_ratio: Inputs!$C$35

Sheet Read Me
A1: DARK STORE REORDER OPTIMISATION MODEL
A3: Question | B3: Where is revenue leaking to stockouts, what actually causes it, and what reorder policy recovers the most net margin?
A4: Headline | B4: ₹1,640,840 per month of revenue is lost to stockouts across 18 dark stores.
A5: Finding | B5: The driver is lead-time mismatch, not demand volatility. Reorder points are sized on a nominal lead time roughly a day shorter than the goods actually take, so each cycle starts short by whole units of cover.
A7: Inputs | B7: Every assumption, in yellow. Change one and the whole model moves.
A8: ROP Model | B8: The four policies, priced. Live formulas end to end.
A9: Sensitivity | B9: Two-way grid: service level x lead-time gap.
A10: Scenario Summary | B10: Scenario Manager layout; also carries the Phase 2 rollout.
A11: Loss Decomposition | B11: The three buckets and who owns each.
A12: Data - * | B12: Query exports behind the analysis.
A14: Model convention | B14: Yellow = input. White = formula. Grey = measured from SQL.
A16: Native Data Table | B16: The Sensitivity grid is written as explicit formulas rather than a native Data Table, so each cell is auditable. To build the native version: put the net-impact formula in a corner cell, select the grid, Data > What-If Analysis > Data Table, row input = service level, column input = L_excess.
A17: Native Scenarios | B17: To re-create Scenario Summary as native scenarios: Data > What-If Analysis > Scenario Manager > Add, changing cell = the service-level cell on ROP Model, one scenario per policy, then Summary with the net-impact cells as result cells.
A19: Caveat | B19: Lost revenue is estimated, not observed — unmet demand is never logged. The corrected estimator is validated against withheld ground truth at 103% coverage (src/validate_estimates.py). The naive SQL figure recovers only 39% and is carried as a floor, not the headline.

Sheet Inputs
A1: INPUTS & ASSUMPTIONS — yellow cells are editable; everything else derives from them
A3: Segment: dairy SKUs at dark stores 3, 7 and 11
B4: Mean demand per SKU per day (units) | C4: 3.0957 | E4: Censored-Poisson MLE (src/estimate_lost_revenue.py), not a raw sales average
B5: SD of daily demand per SKU (units) | C5: 1.7595 | E5: =SQRT(mu_d): demand is Poisson, so variance equals the mean
B6: Nominal lead time (days) | C6: 3.294 | E6: What the current reorder point is sized on (SKU master)
B7: Excess lead time vs peer stores (days) | C7: 1.031 | E7: MEASURED from stock-arrival timing — this is the defect
B8: SD of lead time (days) | C8: 0.49 | E8: Cycle-to-cycle variability in supplier delay
B9: Unit cost | C9: 43.9 | E9: Segment mean
B10: Unit price | C10: 66.05 | E10: Segment mean
B11: Unit margin | C11: 22.15 | E11: =unit_price - unit_cost
B12: Shelf life (days) | C12: 6.7 | E12: Binding constraint on how much safety stock dairy can physically hold
B13: Stores in scope | C13: 3 | E13: Stores 3, 7, 11
B14: Dairy SKUs per store | C14: 30
A16: Economic assumptions
B17: Annual inventory holding rate | C17: 0.25 | E17: Capital + cold chain + space, as a share of unit cost
B18: Replenishment cycle (days) | C18: 7 | E18: Current policy orders one week of cover
B19: Days per month | C19: 30
A21: Measured baseline (from SQL — anchors the model to observed reality)
B22: Lost units per SKU per month, today | C22: 11.841259 | E22: Censored-demand estimate q9, current policy
B23: Segment revenue lost per month | C23: 65476.533 | E23: What the targeted fix is competing for
B24: Segment margin lost per month | C24: 23221.74
A26: Derived quantities
B27: Actual lead time (days) | C27: =L_nom+L_excess | E27: What the goods really take
B28: SD of demand over lead time (units) | C28: =SQRT(L_act*sigma_d^2+mu_d^2*sigma_LT^2) | E28: Combines demand risk and lead-time risk
B29: Order quantity (units) | C29: =mu_d*cycle_days
B30: Replenishment cycles per month | C30: =days_month/cycle_days
B31: Current reorder point (units) | C31: =mu_d*L_nom | E31: Sized on NOMINAL lead time — the defect
B32: Implied z of current policy | C32: =(rop_current-mu_d*L_act)/sigma_DL | E32: Negative: today's reorder point sits BELOW mean lead-time demand
B33: Model calibration factor | C33: =obs_units/(sigma_DL*(NORMDIST(z_current,0,1,FALSE)-z_current*(1-NORMSDIST(z_current)))*cycles_pm) | E33: Solves so the model exactly reproduces today's measured loss; the model is then used only for relative improvement
B34: Holding cost per unit per cycle | C34: =unit_cost*holding_rate*cycle_days/365
B35: Newsvendor critical ratio | C35: =unit_margin/(unit_margin+hold_unit_cycle) | E35: Economically optimal cycle service level
B37: Variance decomposition — is the driver demand or lead time?
B38: Share of variance from demand volatility | C38: =L_act*sigma_d^2/sigma_DL^2
B39: Share of variance from lead-time volatility | C39: =mu_d^2*sigma_LT^2/sigma_DL^2
B40: Units short per cycle from lead-time MEAN gap | C40: =mu_d*L_excess
B41: Read together: lead-time VARIANCE is minor, but the lead-time MEAN gap removes whole units of cover every cycle. The defect is a bias, not noise — so the fix is re-sizing the reorder point, not merely buffering it.

Sheet ROP Model
A1: REORDER POINT MODEL — ROP = (mu_d x L_act) + z x sigma_DL
A3: Every column below is a live formula over the Inputs sheet.
A5: Policy | B5: Service level | C5: z | D5: Reorder point (u) | E5: Safety stock (u) | F5: Loss fn L(z) | G5: Lost units /SKU/mo | H5: Fill rate | I5: Recovery share | J5: Revenue recovered /mo | K5: Margin recovered /mo | L5: Incr. holding /mo | M5: Net margin impact /mo
A6: Current (naive, no safety stock) | B6: =NORMSDIST(C6) | C6: =z_current | D6: =rop_current | E6: =D6-mu_d*L_act | F6: =NORMDIST(C6,0,1,FALSE)-C6*(1-NORMSDIST(C6)) | G6: =sigma_DL*F6*cycles_pm*calib | H6: =1-G6/(mu_d*days_month) | I6: =(obs_units-G6)/obs_units | J6: =I6*seg_rev_loss | K6: =I6*seg_mgn_loss | L6: =((order_qty/2+E6)-(order_qty/2+E6))*unit_cost*(holding_rate/12)*n_stores*n_skus | M6: =K6-L6-N6 | N6: =(MAX(0,(order_qty/2+E6)-shelf_life*mu_d)-MAX(0,(order_qty/2+E6)-shelf_life*mu_d))*unit_cost*cycles_pm*n_stores*n_skus
A7: Policy A — 90% service | B7: 0.9 | C7: =NORMSINV(B7) | D7: =mu_d*L_act+C7*sigma_DL | E7: =D7-mu_d*L_act | F7: =NORMDIST(C7,0,1,FALSE)-C7*(1-NORMSDIST(C7)) | G7: =sigma_DL*F7*cycles_pm*calib | H7: =1-G7/(mu_d*days_month) | I7: =(obs_units-G7)/obs_units | J7: =I7*seg_rev_loss | K7: =I7*seg_mgn_loss | L7: =((order_qty/2+E7)-(order_qty/2+E6))*unit_cost*(holding_rate/12)*n_stores*n_skus | M7: =K7-L7-N7 | N7: =(MAX(0,(order_qty/2+E7)-shelf_life*mu_d)-MAX(0,(order_qty/2+E6)-shelf_life*mu_d))*unit_cost*cycles_pm*n_stores*n_skus
A8: Policy B — 95% service | B8: 0.95 | C8: =NORMSINV(B8) | D8: =mu_d*L_act+C8*sigma_DL | E8: =D8-mu_d*L_act | F8: =NORMDIST(C8,0,1,FALSE)-C8*(1-NORMSDIST(C8)) | G8: =sigma_DL*F8*cycles_pm*calib | H8: =1-G8/(mu_d*days_month) | I8: =(obs_units-G8)/obs_units | J8: =I8*seg_rev_loss | K8: =I8*seg_mgn_loss | L8: =((order_qty/2+E8)-(order_qty/2+E6))*unit_cost*(holding_rate/12)*n_stores*n_skus | M8: =K8-L8-N8 | N8: =(MAX(0,(order_qty/2+E8)-shelf_life*mu_d)-MAX(0,(order_qty/2+E6)-shelf_life*mu_d))*unit_cost*cycles_pm*n_stores*n_skus
A9: Policy C — 99% service | B9: 0.99 | C9: =NORMSINV(B9) | D9: =mu_d*L_act+C9*sigma_DL | E9: =D9-mu_d*L_act | F9: =NORMDIST(C9,0,1,FALSE)-C9*(1-NORMSDIST(C9)) | G9: =sigma_DL*F9*cycles_pm*calib | H9: =1-G9/(mu_d*days_month) | I9: =(obs_units-G9)/obs_units | J9: =I9*seg_rev_loss | K9: =I9*seg_mgn_loss | L9: =((order_qty/2+E9)-(order_qty/2+E6))*unit_cost*(holding_rate/12)*n_stores*n_skus | M9: =K9-L9-N9 | N9: =(MAX(0,(order_qty/2+E9)-shelf_life*mu_d)-MAX(0,(order_qty/2+E6)-shelf_life*mu_d))*unit_cost*cycles_pm*n_stores*n_skus
A11: Shelf-life check — can dairy physically hold this much safety stock?
A12: Policy | B12: Avg inventory (u) | C12: Days of cover | D12: Shelf life (d) | E12: Spoilage risk | F12: Verdict
A13: Current (naive, no safety stock) | B13: =order_qty/2+E6 | C13: =B13/mu_d | D13: =shelf_life | E13: =MAX(0,B13-shelf_life*mu_d) | F13: =IF(C13>shelf_life,"BREACHES shelf life",IF(C13>shelf_life*0.9,"Within 10% of limit","Safe"))
A14: Policy A — 90% service | B14: =order_qty/2+E7 | C14: =B14/mu_d | D14: =shelf_life | E14: =MAX(0,B14-shelf_life*mu_d) | F14: =IF(C14>shelf_life,"BREACHES shelf life",IF(C14>shelf_life*0.9,"Within 10% of limit","Safe"))
A15: Policy B — 95% service | B15: =order_qty/2+E8 | C15: =B15/mu_d | D15: =shelf_life | E15: =MAX(0,B15-shelf_life*mu_d) | F15: =IF(C15>shelf_life,"BREACHES shelf life",IF(C15>shelf_life*0.9,"Within 10% of limit","Safe"))
A16: Policy C — 99% service | B16: =order_qty/2+E9 | C16: =B16/mu_d | D16: =shelf_life | E16: =MAX(0,B16-shelf_life*mu_d) | F16: =IF(C16>shelf_life,"BREACHES shelf life",IF(C16>shelf_life*0.9,"Within 10% of limit","Safe"))
A18: Recommendation
A19: ="Adopt Policy B (95%). It captures "&TEXT(I8/I9,"0.0%")&" of the net value of the "&"99% policy while holding "&TEXT(E9-E8,"0.0")&" fewer units of safety stock per SKU, "&"which keeps days of cover clear of the "&TEXT(shelf_life,"0.0")&"-day dairy shelf life. "&"The newsvendor optimum is "&TEXT(crit_ratio,"0.0%")&", but that sits at the spoilage cliff."

Sheet Sensitivity
A1: SENSITIVITY — net monthly margin impact by service level x excess lead time
A3: Rows vary the lead-time gap; columns vary the target service level. Every cell is a live formula, so this behaves exactly like a native two-way Data Table.
A5: Excess lead time (days) \ Service level | B5: 0.8 | C5: 0.85 | D5: 0.9 | E5: 0.925 | F5: 0.95 | G5: 0.975 | H5: 0.99 | J5: sigma_DL | K5: Baseline lost u/SKU/mo
A6: 0 | B6: =MAX(0,((K6)-(J6*(NORMDIST(NORMSINV(B$5),0,1,FALSE)-NORMSINV(B$5)*(1-NORMSDIST(NORMSINV(B$5))))*cycles_pm*calib))*n_stores*n_skus)*unit_margin-((NORMSINV(B$5))-(-mu_d*A6/J6))*J6*unit_cost*(holding_rate/12)*n_stores*n_skus | C6: =MAX(0,((K6)-(J6*(NORMDIST(NORMSINV(C$5),0,1,FALSE)-NORMSINV(C$5)*(1-NORMSDIST(NORMSINV(C$5))))*cycles_pm*calib))*n_stores*n_skus)*unit_margin-((NORMSINV(C$5))-(-mu_d*A6/J6))*J6*unit_cost*(holding_rate/12)*n_stores*n_skus | D6: =MAX(0,((K6)-(J6*(NORMDIST(NORMSINV(D$5),0,1,FALSE)-NORMSINV(D$5)*(1-NORMSDIST(NORMSINV(D$5))))*cycles_pm*calib))*n_stores*n_skus)*unit_margin-((NORMSINV(D$5))-(-mu_d*A6/J6))*J6*unit_cost*(holding_rate/12)*n_stores*n_skus | E6: =MAX(0,((K6)-(J6*(NORMDIST(NORMSINV(E$5),0,1,FALSE)-NORMSINV(E$5)*(1-NORMSDIST(NORMSINV(E$5))))*cycles_pm*calib))*n_stores*n_skus)*unit_margin-((NORMSINV(E$5))-(-mu_d*A6/J6))*J6*unit_cost*(holding_rate/12)*n_stores*n_skus | F6: =MAX(0,((K6)-(J6*(NORMDIST(NORMSINV(F$5),0,1,FALSE)-NORMSINV(F$5)*(1-NORMSDIST(NORMSINV(F$5))))*cycles_pm*calib))*n_stores*n_skus)*unit_margin-((NORMSINV(F$5))-(-mu_d*A6/J6))*J6*unit_cost*(holding_rate/12)*n_stores*n_skus | G6: =MAX(0,((K6)-(J6*(NORMDIST(NORMSINV(G$5),0,1,FALSE)-NORMSINV(G$5)*(1-NORMSDIST(NORMSINV(G$5))))*cycles_pm*calib))*n_stores*n_skus)*unit_margin-((NORMSINV(G$5))-(-mu_d*A6/J6))*J6*unit_cost*(holding_rate/12)*n_stores*n_skus | H6: =MAX(0,((K6)-(J6*(NORMDIST(NORMSINV(H$5),0,1,FALSE)-NORMSINV(H$5)*(1-NORMSDIST(NORMSINV(H$5))))*cycles_pm*calib))*n_stores*n_skus)*unit_margin-((NORMSINV(H$5))-(-mu_d*A6/J6))*J6*unit_cost*(holding_rate/12)*n_stores*n_skus | J6: =SQRT((L_nom+A6)*sigma_d^2+mu_d^2*sigma_LT^2) | K6: =J6*(NORMDIST((-mu_d*A6/J6),0,1,FALSE)-(-mu_d*A6/J6)*(1-NORMSDIST((-mu_d*A6/J6))))*cycles_pm*calib
A7: 0.5 | B7: =MAX(0,((K7)-(J7*(NORMDIST(NORMSINV(B$5),0,1,FALSE)-NORMSINV(B$5)*(1-NORMSDIST(NORMSINV(B$5))))*cycles_pm*calib))*n_stores*n_skus)*unit_margin-((NORMSINV(B$5))-(-mu_d*A7/J7))*J7*unit_cost*(holding_rate/12)*n_stores*n_skus | C7: =MAX(0,((K7)-(J7*(NORMDIST(NORMSINV(C$5),0,1,FALSE)-NORMSINV(C$5)*(1-NORMSDIST(NORMSINV(C$5))))*cycles_pm*calib))*n_stores*n_skus)*unit_margin-((NORMSINV(C$5))-(-mu_d*A7/J7))*J7*unit_cost*(holding_rate/12)*n_stores*n_skus | D7: =MAX(0,((K7)-(J7*(NORMDIST(NORMSINV(D$5),0,1,FALSE)-NORMSINV(D$5)*(1-NORMSDIST(NORMSINV(D$5))))*cycles_pm*calib))*n_stores*n_skus)*unit_margin-((NORMSINV(D$5))-(-mu_d*A7/J7))*J7*unit_cost*(holding_rate/12)*n_stores*n_skus | E7: =MAX(0,((K7)-(J7*(NORMDIST(NORMSINV(E$5),0,1,FALSE)-NORMSINV(E$5)*(1-NORMSDIST(NORMSINV(E$5))))*cycles_pm*calib))*n_stores*n_skus)*unit_margin-((NORMSINV(E$5))-(-mu_d*A7/J7))*J7*unit_cost*(holding_rate/12)*n_stores*n_skus | F7: =MAX(0,((K7)-(J7*(NORMDIST(NORMSINV(F$5),0,1,FALSE)-NORMSINV(F$5)*(1-NORMSDIST(NORMSINV(F$5))))*cycles_pm*calib))*n_stores*n_skus)*unit_margin-((NORMSINV(F$5))-(-mu_d*A7/J7))*J7*unit_cost*(holding_rate/12)*n_stores*n_skus | G7: =MAX(0,((K7)-(J7*(NORMDIST(NORMSINV(G$5),0,1,FALSE)-NORMSINV(G$5)*(1-NORMSDIST(NORMSINV(G$5))))*cycles_pm*calib))*n_stores*n_skus)*unit_margin-((NORMSINV(G$5))-(-mu_d*A7/J7))*J7*unit_cost*(holding_rate/12)*n_stores*n_skus | H7: =MAX(0,((K7)-(J7*(NORMDIST(NORMSINV(H$5),0,1,FALSE)-NORMSINV(H$5)*(1-NORMSDIST(NORMSINV(H$5))))*cycles_pm*calib))*n_stores*n_skus)*unit_margin-((NORMSINV(H$5))-(-mu_d*A7/J7))*J7*unit_cost*(holding_rate/12)*n_stores*n_skus | J7: =SQRT((L_nom+A7)*sigma_d^2+mu_d^2*sigma_LT^2) | K7: =J7*(NORMDIST((-mu_d*A7/J7),0,1,FALSE)-(-mu_d*A7/J7)*(1-NORMSDIST((-mu_d*A7/J7))))*cycles_pm*calib
A8: 1 | B8: =MAX(0,((K8)-(J8*(NORMDIST(NORMSINV(B$5),0,1,FALSE)-NORMSINV(B$5)*(1-NORMSDIST(NORMSINV(B$5))))*cycles_pm*calib))*n_stores*n_skus)*unit_margin-((NORMSINV(B$5))-(-mu_d*A8/J8))*J8*unit_cost*(holding_rate/12)*n_stores*n_skus | C8: =MAX(0,((K8)-(J8*(NORMDIST(NORMSINV(C$5),0,1,FALSE)-NORMSINV(C$5)*(1-NORMSDIST(NORMSINV(C$5))))*cycles_pm*calib))*n_stores*n_skus)*unit_margin-((NORMSINV(C$5))-(-mu_d*A8/J8))*J8*unit_cost*(holding_rate/12)*n_stores*n_skus | D8: =MAX(0,((K8)-(J8*(NORMDIST(NORMSINV(D$5),0,1,FALSE)-NORMSINV(D$5)*(1-NORMSDIST(NORMSINV(D$5))))*cycles_pm*calib))*n_stores*n_skus)*unit_margin-((NORMSINV(D$5))-(-mu_d*A8/J8))*J8*unit_cost*(holding_rate/12)*n_stores*n_skus | E8: =MAX(0,((K8)-(J8*(NORMDIST(NORMSINV(E$5),0,1,FALSE)-NORMSINV(E$5)*(1-NORMSDIST(NORMSINV(E$5))))*cycles_pm*calib))*n_stores*n_skus)*unit_margin-((NORMSINV(E$5))-(-mu_d*A8/J8))*J8*unit_cost*(holding_rate/12)*n_stores*n_skus | F8: =MAX(0,((K8)-(J8*(NORMDIST(NORMSINV(F$5),0,1,FALSE)-NORMSINV(F$5)*(1-NORMSDIST(NORMSINV(F$5))))*cycles_pm*calib))*n_stores*n_skus)*unit_margin-((NORMSINV(F$5))-(-mu_d*A8/J8))*J8*unit_cost*(holding_rate/12)*n_stores*n_skus | G8: =MAX(0,((K8)-(J8*(NORMDIST(NORMSINV(G$5),0,1,FALSE)-NORMSINV(G$5)*(1-NORMSDIST(NORMSINV(G$5))))*cycles_pm*calib))*n_stores*n_skus)*unit_margin-((NORMSINV(G$5))-(-mu_d*A8/J8))*J8*unit_cost*(holding_rate/12)*n_stores*n_skus | H8: =MAX(0,((K8)-(J8*(NORMDIST(NORMSINV(H$5),0,1,FALSE)-NORMSINV(H$5)*(1-NORMSDIST(NORMSINV(H$5))))*cycles_pm*calib))*n_stores*n_skus)*unit_margin-((NORMSINV(H$5))-(-mu_d*A8/J8))*J8*unit_cost*(holding_rate/12)*n_stores*n_skus | J8: =SQRT((L_nom+A8)*sigma_d^2+mu_d^2*sigma_LT^2) | K8: =J8*(NORMDIST((-mu_d*A8/J8),0,1,FALSE)-(-mu_d*A8/J8)*(1-NORMSDIST((-mu_d*A8/J8))))*cycles_pm*calib
A9: 1.5 | B9: =MAX(0,((K9)-(J9*(NORMDIST(NORMSINV(B$5),0,1,FALSE)-NORMSINV(B$5)*(1-NORMSDIST(NORMSINV(B$5))))*cycles_pm*calib))*n_stores*n_skus)*unit_margin-((NORMSINV(B$5))-(-mu_d*A9/J9))*J9*unit_cost*(holding_rate/12)*n_stores*n_skus | C9: =MAX(0,((K9)-(J9*(NORMDIST(NORMSINV(C$5),0,1,FALSE)-NORMSINV(C$5)*(1-NORMSDIST(NORMSINV(C$5))))*cycles_pm*calib))*n_stores*n_skus)*unit_margin-((NORMSINV(C$5))-(-mu_d*A9/J9))*J9*unit_cost*(holding_rate/12)*n_stores*n_skus | D9: =MAX(0,((K9)-(J9*(NORMDIST(NORMSINV(D$5),0,1,FALSE)-NORMSINV(D$5)*(1-NORMSDIST(NORMSINV(D$5))))*cycles_pm*calib))*n_stores*n_skus)*unit_margin-((NORMSINV(D$5))-(-mu_d*A9/J9))*J9*unit_cost*(holding_rate/12)*n_stores*n_skus | E9: =MAX(0,((K9)-(J9*(NORMDIST(NORMSINV(E$5),0,1,FALSE)-NORMSINV(E$5)*(1-NORMSDIST(NORMSINV(E$5))))*cycles_pm*calib))*n_stores*n_skus)*unit_margin-((NORMSINV(E$5))-(-mu_d*A9/J9))*J9*unit_cost*(holding_rate/12)*n_stores*n_skus | F9: =MAX(0,((K9)-(J9*(NORMDIST(NORMSINV(F$5),0,1,FALSE)-NORMSINV(F$5)*(1-NORMSDIST(NORMSINV(F$5))))*cycles_pm*calib))*n_stores*n_skus)*unit_margin-((NORMSINV(F$5))-(-mu_d*A9/J9))*J9*unit_cost*(holding_rate/12)*n_stores*n_skus | G9: =MAX(0,((K9)-(J9*(NORMDIST(NORMSINV(G$5),0,1,FALSE)-NORMSINV(G$5)*(1-NORMSDIST(NORMSINV(G$5))))*cycles_pm*calib))*n_stores*n_skus)*unit_margin-((NORMSINV(G$5))-(-mu_d*A9/J9))*J9*unit_cost*(holding_rate/12)*n_stores*n_skus | H9: =MAX(0,((K9)-(J9*(NORMDIST(NORMSINV(H$5),0,1,FALSE)-NORMSINV(H$5)*(1-NORMSDIST(NORMSINV(H$5))))*cycles_pm*calib))*n_stores*n_skus)*unit_margin-((NORMSINV(H$5))-(-mu_d*A9/J9))*J9*unit_cost*(holding_rate/12)*n_stores*n_skus | J9: =SQRT((L_nom+A9)*sigma_d^2+mu_d^2*sigma_LT^2) | K9: =J9*(NORMDIST((-mu_d*A9/J9),0,1,FALSE)-(-mu_d*A9/J9)*(1-NORMSDIST((-mu_d*A9/J9))))*cycles_pm*calib
A10: 2 | B10: =MAX(0,((K10)-(J10*(NORMDIST(NORMSINV(B$5),0,1,FALSE)-NORMSINV(B$5)*(1-NORMSDIST(NORMSINV(B$5))))*cycles_pm*calib))*n_stores*n_skus)*unit_margin-((NORMSINV(B$5))-(-mu_d*A10/J10))*J10*unit_cost*(holding_rate/12)*n_stores*n_skus | C10: =MAX(0,((K10)-(J10*(NORMDIST(NORMSINV(C$5),0,1,FALSE)-NORMSINV(C$5)*(1-NORMSDIST(NORMSINV(C$5))))*cycles_pm*calib))*n_stores*n_skus)*unit_margin-((NORMSINV(C$5))-(-mu_d*A10/J10))*J10*unit_cost*(holding_rate/12)*n_stores*n_skus | D10: =MAX(0,((K10)-(J10*(NORMDIST(NORMSINV(D$5),0,1,FALSE)-NORMSINV(D$5)*(1-NORMSDIST(NORMSINV(D$5))))*cycles_pm*calib))*n_stores*n_skus)*unit_margin-((NORMSINV(D$5))-(-mu_d*A10/J10))*J10*unit_cost*(holding_rate/12)*n_stores*n_skus | E10: =MAX(0,((K10)-(J10*(NORMDIST(NORMSINV(E$5),0,1,FALSE)-NORMSINV(E$5)*(1-NORMSDIST(NORMSINV(E$5))))*cycles_pm*calib))*n_stores*n_skus)*unit_margin-((NORMSINV(E$5))-(-mu_d*A10/J10))*J10*unit_cost*(holding_rate/12)*n_stores*n_skus | F10: =MAX(0,((K10)-(J10*(NORMDIST(NORMSINV(F$5),0,1,FALSE)-NORMSINV(F$5)*(1-NORMSDIST(NORMSINV(F$5))))*cycles_pm*calib))*n_stores*n_skus)*unit_margin-((NORMSINV(F$5))-(-mu_d*A10/J10))*J10*unit_cost*(holding_rate/12)*n_stores*n_skus | G10: =MAX(0,((K10)-(J10*(NORMDIST(NORMSINV(G$5),0,1,FALSE)-NORMSINV(G$5)*(1-NORMSDIST(NORMSINV(G$5))))*cycles_pm*calib))*n_stores*n_skus)*unit_margin-((NORMSINV(G$5))-(-mu_d*A10/J10))*J10*unit_cost*(holding_rate/12)*n_stores*n_skus | H10: =MAX(0,((K10)-(J10*(NORMDIST(NORMSINV(H$5),0,1,FALSE)-NORMSINV(H$5)*(1-NORMSDIST(NORMSINV(H$5))))*cycles_pm*calib))*n_stores*n_skus)*unit_margin-((NORMSINV(H$5))-(-mu_d*A10/J10))*J10*unit_cost*(holding_rate/12)*n_stores*n_skus | J10: =SQRT((L_nom+A10)*sigma_d^2+mu_d^2*sigma_LT^2) | K10: =J10*(NORMDIST((-mu_d*A10/J10),0,1,FALSE)-(-mu_d*A10/J10)*(1-NORMSDIST((-mu_d*A10/J10))))*cycles_pm*calib
A12: The measured gap is the 1.0-day row. Read ACROSS it and the value barely moves (80% -> 99% adds ~12%); read DOWN the columns and it triples. The size of the lead-time gap, not the service level chosen to cover it, is what drives the prize — which is why the recommendation is to re-size the reorder point to the lead time actually delivered, and why the exact service level inside the 90-99% band is a second-order choice.

Sheet Scenario Summary
A1: SCENARIO SUMMARY — three service-level policies
A3: Laid out the way Excel's Scenario Manager reports, but formula-driven so it stays live. See Read Me to re-create it as native scenarios.
A5: Result cell | B5: Current | C5: Policy A (90%) | D5: Policy B (95%) | E5: Policy C (99%) | F5: Comment
A6: Target service level | B6: ='ROP Model'!B6 | C6: ='ROP Model'!B7 | D6: ='ROP Model'!B8 | E6: ='ROP Model'!B9
A7: Reorder point (units/SKU) | B7: ='ROP Model'!D6 | C7: ='ROP Model'!D7 | D7: ='ROP Model'!D8 | E7: ='ROP Model'!D9 | F7: Current is sized on nominal lead time
A8: Safety stock (units/SKU) | B8: ='ROP Model'!E6 | C8: ='ROP Model'!E7 | D8: ='ROP Model'!E8 | E8: ='ROP Model'!E9 | F8: Negative today = structurally short
A9: Lost units /SKU/month | B9: ='ROP Model'!G6 | C9: ='ROP Model'!G7 | D9: ='ROP Model'!G8 | E9: ='ROP Model'!G9
A10: Fill rate | B10: ='ROP Model'!H6 | C10: ='ROP Model'!H7 | D10: ='ROP Model'!H8 | E10: ='ROP Model'!H9
A11: Revenue recovered /month | B11: ='ROP Model'!J6 | C11: ='ROP Model'!J7 | D11: ='ROP Model'!J8 | E11: ='ROP Model'!J9 | F11: Against measured segment loss
A12: Margin recovered /month | B12: ='ROP Model'!K6 | C12: ='ROP Model'!K7 | D12: ='ROP Model'!K8 | E12: ='ROP Model'!K9
A13: Incremental holding /month | B13: ='ROP Model'!L6 | C13: ='ROP Model'!L7 | D13: ='ROP Model'!L8 | E13: ='ROP Model'!L9 | F13: Cost of carrying the buffer
A14: NET margin impact /month | B14: ='ROP Model'!M6 | C14: ='ROP Model'!M7 | D14: ='ROP Model'!M8 | E14: ='ROP Model'!M9 | F14: The decision number
A16: Phase 2 — same policy rolled out network-wide
A17: Scope | B17: Stores | C17: Revenue recovered /mo | D17: Margin recovered /mo | E17: Holding cost /mo | F17: Net margin /mo
A18: Targeted: dairy @ stores 3, 7, 11 | B18: 3 | C18: ='ROP Model'!J8 | D18: ='ROP Model'!K8 | E18: ='ROP Model'!L8 | F18: ='ROP Model'!M8
A19: Network rollout, all categories (ex stores 14 & 16) | B19: 16 | C19: 1029715 | D19: 367049.49 | E19: 27813.15 | F19: 339236.34
A20: Stores 14 & 16 — routed to operations, NOT reorder policy | B20: 2 | C20: n/a | D20: n/a | E20: n/a | F20: n/a
A22: Stores 14 and 16 are excluded on purpose. Their stock disappears without being sold, so raising their reorder point would fund the leak rather than close it. Sizing a recovery for them here would be the single easiest way to make this model wrong.

Sheet Loss Decomposition
A1: WHERE THE MONEY GOES — three buckets, three different owners
A3: Total estimated revenue lost to stockouts: ₹1,640,840 per month across 18 stores.
A5: Bucket | B5: Revenue lost /mo | C5: Margin lost /mo | D5: % of total | E5: Cells | F5: Fix — and who owns it
A6: C — Systemic: no safety stock | B6: 1018344 | C6: 363116 | D6: 0.621 | E6: 93 | F6: Supply planning, phase 2: the network carries zero safety stock everywhere. Roll out after the pilot.
A7: A — Operational shrinkage | B7: 557019 | C7: 199320 | D7: 0.339 | E7: 12 | F7: Operations audit at stores 14 & 16. Stock is leaving without being sold; a reorder-point change cannot touch this.
A8: B — Lead-time mismatch (dairy) | B8: 65477 | C8: 23222 | D8: 0.04 | E8: 3 | F8: Supply planning: re-size the dairy reorder point at stores 3, 7, 11 to the lead time actually delivered. THIS MEMO.
A9: TOTAL | B9: =SUM(B6:B8) | C9: =SUM(C6:C8)

Sheet Data - Lost Revenue
A1: LOST REVENUE BY STORE — naive SQL estimate vs censored-demand estimate
A3: The naive trailing-7-day method recovers only ~39% of true lost revenue: stockouts happen on above-average days, so a mean-based baseline cannot price the spike. The corrected column is the planning number; the naive one is the defensible floor.
A6: Store | B6: Stockout days | C6: Naive estimate (90d) | D6: Corrected estimate (90d) | E6: Corrected margin (90d)
A7: 14 | B7: 2674 | C7: 359795.92 | D7: 848614.09 | E7: 304006.12
A8: 16 | B8: 2492 | C8: 387199.94 | D8: 822441.71 | E8: 293954.91
A9: 7 | B9: 829 | C9: 130727.8 | D9: 270441.59 | E9: 96531.95
A10: 3 | B10: 889 | C10: 112377.55 | D10: 248666.45 | E10: 88097.19
A11: 11 | B11: 844 | C11: 89072.27 | D11: 232225.1 | E11: 83222.41
A12: 8 | B12: 607 | C12: 76450.46 | D12: 218759.31 | E12: 77640.25
A13: 5 | B13: 603 | C13: 77218.64 | D13: 208236.24 | E13: 74943.64
A14: 1 | B14: 629 | C14: 64920.41 | D14: 206070.59 | E14: 72999.62
A15: 10 | B15: 568 | C15: 67929.11 | D15: 196628.87 | E15: 69779.01
A16: 13 | B16: 553 | C16: 65941.9 | D16: 196606.38 | E16: 70106.49
A17: 6 | B17: 607 | C17: 58510.93 | D17: 193038.87 | E17: 68246.28
A18: 17 | B18: 577 | C18: 61171.51 | D18: 191157.85 | E18: 67489.74
... A24: 15 | B24: 664 | C24: 41509.46 | D24: 167606.74 | E24: 60048.23

Sheet Data - Stockout Rates
A1: STOCKOUT RATE BY STORE x CATEGORY (Q1)
A3: Heat map: stores 14 and 16 are hot across EVERY category (an ops problem); stores 3, 7 and 11 are hot in dairy only (a supply problem).
A5: Store | B5: beverages | C5: dairy | D5: household | E5: personal_care | F5: produce | G5: snacks
A6: 1 | B6: 0.047 | C6: 0.0448 | D6: 0.0293 | E6: 0.0367 | F6: 0.0363 | G6: 0.0389
A7: 2 | B7: 0.04 | C7: 0.0474 | D7: 0.0381 | E7: 0.0348 | F7: 0.0463 | G7: 0.04
A8: 3 | B8: 0.0396 | C8: 0.1289 | D8: 0.0415 | E8: 0.0359 | F8: 0.0419 | G8: 0.0415
A9: 4 | B9: 0.0422 | C9: 0.0456 | D9: 0.0281 | E9: 0.0378 | F9: 0.043 | G9: 0.0437
A10: 5 | B10: 0.0378 | C10: 0.0404 | D10: 0.0322 | E10: 0.0374 | F10: 0.0356 | G10: 0.04
A11: 6 | B11: 0.0415 | C11: 0.0489 | D11: 0.0337 | E11: 0.0285 | F11: 0.0359 | G11: 0.0363
A12: 7 | B12: 0.0393 | C12: 0.1344 | D12: 0.0296 | E12: 0.0285 | F12: 0.0319 | G12: 0.0433
A13: 8 | B13: 0.0422 | C13: 0.0415 | D13: 0.0293 | E13: 0.0348 | F13: 0.0341 | G13: 0.043
A14: 9 | B14: 0.0478 | C14: 0.0456 | D14: 0.0319 | E14: 0.0278 | F14: 0.0422 | G14: 0.0441
A15: 10 | B15: 0.0404 | C15: 0.0381 | D15: 0.0285 | E15: 0.0263 | F15: 0.0396 | G15: 0.0374
A16: 11 | B16: 0.0452 | C16: 0.1252 | D16: 0.0359 | E16: 0.0259 | F16: 0.0381 | G16: 0.0422
A17: 12 | B17: 0.0415 | C17: 0.0493 | D17: 0.0341 | E17: 0.0274 | F17: 0.0481 | G17: 0.0381
... A23: 18 | B23: 0.0426 | C23: 0.0437 | D23: 0.0359 | E23: 0.0407 | F23: 0.0422 | G23: 0.0378
A26: store_id | B26: category | C26: n_store_days | D26: n_stockout_days | E26: stockout_rate_pct | F26: stockout_rank
A27: 14 | B27: dairy | C27: 2700 | D27: 568 | E27: 21.04 | F27: 1
A28: 16 | B28: dairy | C28: 2700 | D28: 537 | E28: 19.89 | F28: 2
A29: 14 | B29: produce | C29: 2700 | D29: 477 | E29: 17.67 | F29: 3
A30: 14 | B30: beverages | C30: 2700 | D30: 439 | E30: 16.26 | F30: 4
A31: 16 | B31: produce | C31: 2700 | D31: 430 | E31: 15.93 | F31: 5
A32: 14 | B32: personal_care | C32: 2700 | D32: 404 | E32: 14.96 | F32: 6
A33: 14 | B33: snacks | C33: 2700 | D33: 400 | E33: 14.81 | F33: 7
A34: 16 | B34: personal_care | C34: 2700 | D34: 392 | E34: 14.52 | F34: 8
A35: 16 | B35: beverages | C35: 2700 | D35: 387 | E35: 14.33 | F35: 9
A36: 14 | B36: household | C36: 2700 | D36: 386 | E36: 14.3 | F36: 10
A37: 16 | B37: snacks | C37: 2700 | D37: 383 | E37: 14.19 | F37: 11
A38: 7 | B38: dairy | C38: 2700 | D38: 363 | E38: 13.44 | F38: 12
... A134: 11 | B134: personal_care | C134: 2700 | D134: 70 | E134: 2.59 | F134: 108

Sheet Data - Lead Time
A1: LEAD TIME EVIDENCE (Q4 + Q11)
A3: Q4: stockout rate climbs monotonically with lead time — the signature of a reorder point that carries no buffer.
A5: lead_time_days | B5: stockout_rate_pct | C5: n_observations | D5: n_skus
A6: 1 | B6: 3.78 | C6: 102060 | D6: 63
A7: 2 | B7: 5.72 | C7: 127980 | D7: 79
A8: 3 | B8: 7.1 | C8: 38880 | D8: 24
A9: 4 | B9: 8.2 | C9: 22680 | D9: 14
A12: Q11: lead time measured from stock-arrival timing, per store x category. 'Excess' is the gap versus other stores for the same category.
A14: store_id | B14: category | C14: nominal_lt | D14: observed_lt | E14: n_cycles | F14: peer_observed_lt | G14: excess_lead_time_days
A15: 1 | B15: beverages | C15: 1.597 | D15: 1.55 | E15: 380 | F15: 1.523 | G15: 0.027
A16: 1 | B16: dairy | C16: 3.28 | D16: 2.723 | E16: 318 | F16: 2.774 | G16: -0.051
A17: 1 | B17: household | C17: 1.528 | D17: 1.425 | E17: 339 | F17: 1.452 | G17: -0.028
A18: 1 | B18: personal_care | C18: 1.583 | D18: 1.438 | E18: 336 | F18: 1.469 | G18: -0.032
A19: 1 | B19: produce | C19: 2.245 | D19: 2.01 | E19: 314 | F19: 2.006 | G19: 0.003
A20: 1 | B20: snacks | C20: 1.36 | D20: 1.321 | E20: 364 | F20: 1.324 | G20: -0.003
A21: 2 | B21: beverages | C21: 1.574 | D21: 1.53 | E21: 338 | F21: 1.523 | G21: 0.007
A22: 2 | B22: dairy | C22: 3.268 | D22: 2.852 | E22: 310 | F22: 2.774 | G22: 0.077
A23: 2 | B23: household | C23: 1.53 | D23: 1.485 | E23: 328 | F23: 1.452 | G23: 0.032
A24: 2 | B24: personal_care | C24: 1.593 | D24: 1.518 | E24: 305 | F24: 1.469 | G24: 0.049
A25: 2 | B25: produce | C25: 2.247 | D25: 2.031 | E25: 295 | F25: 2.006 | G25: 0.024
A26: 2 | B26: snacks | C26: 1.34 | D26: 1.325 | E26: 379 | F26: 1.324 | G26: 0
... A122: 18 | B122: snacks | C122: 1.379 | D122: 1.329 | E122: 343 | F122: 1.324 | G122: 0.005

Sheet Data - Root Cause
A1: ROOT CAUSE SPLIT (Q5)
A3: Demand-driven = sold above the median and still ran out. Supply-driven = there was nothing on the shelf to sell.
A5: Store | B5: Demand-driven | C5: Supply-driven | D5: Supply share
A6: 1 | B6: 264 | C6: 365 | D6: 0.58028617
A7: 2 | B7: 277 | C7: 389 | D7: 0.58408408
A8: 3 | B8: 309 | C8: 580 | D8: 0.65241845
A9: 4 | B9: 294 | C9: 355 | D9: 0.54699538
A10: 5 | B10: 245 | C10: 358 | D10: 0.59369818
A11: 6 | B11: 266 | C11: 341 | D11: 0.56177924
A12: 7 | B12: 255 | C12: 574 | D12: 0.69240048
A13: 8 | B13: 262 | C13: 345 | D13: 0.56836903
A14: 9 | B14: 284 | C14: 362 | D14: 0.56037152
A15: 10 | B15: 226 | C15: 342 | D15: 0.60211268
A16: 11 | B16: 289 | C16: 555 | D16: 0.65758294
A17: 12 | B17: 252 | C17: 392 | D17: 0.60869565
... A23: 18 | B23: 288 | C23: 368 | D23: 0.56097561

Sheet Data - Weekend
A1: WEEKEND DEMAND LIFT (Q3)
A3: Only snacks and beverages lift on Fri/Sat. Dairy is flat — which rules out weekend demand as the explanation for the dairy stockouts.
A5: category | B5: avg_weekend_units | C5: avg_weekday_units | D5: weekend_lift_pct
A6: beverages | B6: 2.818 | C6: 2.127 | D6: 32.5
A7: snacks | B7: 2.55 | C7: 1.925 | D7: 32.4
A8: household | B8: 2.16 | C8: 2.149 | D8: 0.5
A9: produce | B9: 2.321 | C9: 2.328 | D9: -0.3
A10: dairy | B10: 2.547 | C10: 2.564 | D10: -0.6
A11: personal_care | B11: 1.771 | C11: 1.788 | D11: -1
